venvasion-0.1.2.data/data/bin/activate
venvasion-0.1.2.dist-info/METADATA
venvasion-0.1.2.dist-info/WHEEL
venvasion-0.1.2.dist-info/entry_points.txt
venvasion/__init__.py
venvasion/py.typed
venvasion-0.1.2.dist-info/RECORD
