Metadata-Version: 2.1
Name: venvasion
Version: 0.1.2
Summary: Arbitrary code execution when activating a virtual environment after install a wheel
Author-Email: konstin <konstin@mailbox.org>
Project-URL: github, https://github.com/konstin/venvasion
Requires-Python: >=3.9.0
